gearbox/__init__.py
gearbox/actions.py
gearbox/buffer_actions.py
gearbox/compilation.py
gearbox/constants.py
gearbox/dbg.py
gearbox/default.css
gearbox/description.py
gearbox/description_actions.py
gearbox/dti_translate.py
gearbox/file_actions.py
gearbox/foreign_win.py
gearbox/gearbox.png
gearbox/graph.py
gearbox/graph_actions.py
gearbox/graph_sim_status.py
gearbox/gtkwave.py
gearbox/gtkwave.tcl
gearbox/gtkwave_actions.py
gearbox/gtkwave_intf.py
gearbox/gtkwaverc
gearbox/gv_utils.py
gearbox/html_utils.py
gearbox/layout.py
gearbox/logo.png
gearbox/main.py
gearbox/main_window.py
gearbox/minibuffer.py
gearbox/modeline.py
gearbox/node.py
gearbox/node_abstract.py
gearbox/node_model.py
gearbox/node_search.py
gearbox/pipe.py
gearbox/popup_desc.py
gearbox/port.py
gearbox/pygears_proxy.py
gearbox/saver.py
gearbox/scene.py
gearbox/sim_actions.py
gearbox/sniper.py
gearbox/theme.py
gearbox/timekeep.py
gearbox/timestep_modeline.py
gearbox/toggle_actions.py
gearbox/utils.py
gearbox/which_key.py
gearbox/window_actions.py
pygears_gearbox-0.0.1.dist-info/LICENSE
pygears_gearbox-0.0.1.dist-info/METADATA
pygears_gearbox-0.0.1.dist-info/WHEEL
pygears_gearbox-0.0.1.dist-info/entry_points.txt
pygears_gearbox-0.0.1.dist-info/top_level.txt
pygears_gearbox-0.0.1.dist-info/RECORD
